<?xml version="1.0" encoding="utf-8"?>
<samples n="NOR0013">
 <sample>
  <p n="NOR0013883">
   <s>
    <w>
     Daa
    </w>
    <w>
     Georg
    </w>
    <w>
     ikkje
    </w>
    <w>
     svara
    </w>
    <w>
     ,
    </w>
    <w>
     slutta
    </w>
    <w>
     han
    </w>
    <w>
     ;
    </w>
    <w>
     so
    </w>
    <w>
     sette
    </w>
    <w>
     han
    </w>
    <w>
     seg
    </w>
    <w>
     til
    </w>
    <w>
     med
    </w>
    <w>
     Hovude
    </w>
    <w>
     i
    </w>
    <w>
     Hendane
    </w>
    <w>
     og
    </w>
    <w>
     smaasnakka
    </w>
    <w>
     ;
    </w>
    <w>
     tok
    </w>
    <w>
     sistpaa
    </w>
    <w>
     til
    </w>
    <w>
     aa
    </w>
    <w>
     syngje
    </w>
    <w>
     .
    </w>
   </s>
  </p>
  <p n="NOR0013884">
   <s>
    <w>
     «
    </w>
    <w>
     Ja
    </w>
    <w>
     ,
    </w>
    <w>
     ja
    </w>
    <w>
     »
    </w>
    <w>
     ,
    </w>
    <w>
     sagde
    </w>
    <w>
     han
    </w>
    <w>
     ,
    </w>
    <w>
     «
    </w>
    <w>
     Gud
    </w>
    <w>
     hjælpe
    </w>
    <w>
     oss
    </w>
    <w>
     alle
    </w>
    <w>
     som
    </w>
    <w>
     syge
    </w>
    <w>
     og
    </w>
    <w>
     sorrigfulde
    </w>
    <w>
     er
    </w>
    <w>
     ,
    </w>
    <w>
     hvad
    </w>
    <w>
     enten
    </w>
    <w>
     vi
    </w>
    <w>
     ere
    </w>
    <w>
     fjern
    </w>
    <w>
     eller
    </w>
    <w>
     nær
    </w>
    <w>
     .
    </w>
   </s>
   <s>
    <w>
     Du
    </w>
    <w>
     ?
    </w>
   </s>
   <s>
    <w>
     Du
    </w>
    <w>
     ?
    </w>
    <w>
     »
    </w>
    <w>
     han
    </w>
    <w>
     vende
    </w>
    <w>
     seg
    </w>
    <w>
     til
    </w>
    <w>
     den
    </w>
    <w>
     ,
    </w>
    <w>
     som
    </w>
    <w>
     sat
    </w>
    <w>
     ved
    </w>
    <w>
     Sida
    </w>
    <w>
     av
    </w>
    <w>
     han
    </w>
    <w>
     ;
    </w>
    <w>
     «
    </w>
    <w>
     Du
    </w>
    <w>
     ?
    </w>
   </s>
   <s>
    <w>
     vét
    </w>
    <w>
     du
    </w>
    <w>
     hva
    </w>
    <w>
     ?
    </w>
    <w>
     »
    </w>
    <w>
     og
    </w>
    <w>
     so
    </w>
    <w>
     gav
    </w>
    <w>
     han
    </w>
    <w>
     seg
    </w>
    <w>
     til
    </w>
    <w>
     aa
    </w>
    <w>
     tala
    </w>
    <w>
     um
    </w>
    <w>
     Kona
    </w>
    <w>
     si
    </w>
    <w>
     .
    </w>
   </s>
   <s>
    <w>
     Ho
    </w>
    <w>
     var
    </w>
    <w>
     so
    </w>
    <w>
     ,
    </w>
    <w>
     og
    </w>
    <w>
     ho
    </w>
    <w>
     var
    </w>
    <w>
     so
    </w>
    <w>
     ;
    </w>
    <w>
     og
    </w>
    <w>
     dei
    </w>
    <w>
     sagde
    </w>
    <w>
     so
    </w>
    <w>
     tidt
    </w>
    <w>
     til
    </w>
    <w>
     han
    </w>
    <w>
     :
    </w>
    <w>
     du
    </w>
    <w>
     Hummelvik
    </w>
    <w>
     ,
    </w>
    <w>
     du
    </w>
    <w>
     skal
    </w>
    <w>
     skilja
    </w>
    <w>
     deg
    </w>
    <w>
     med
    </w>
    <w>
     Martine
    </w>
    <w>
     Men
    </w>
    <w>
     det
    </w>
    <w>
     vilde
    </w>
    <w>
     han
    </w>
    <w>
     ikkje
    </w>
    <w>
     .
    </w>
   </s>
   <s>
    <w>
     Nei
    </w>
    <w>
     .
    </w>
   </s>
   <s>
    <w>
     Det
    </w>
    <w>
     vilde
    </w>
    <w>
     han
    </w>
    <w>
     ikkje
    </w>
    <w>
     .
    </w>
   </s>
   <s>
    <w>
     Aldri
    </w>
    <w>
     i
    </w>
    <w>
     Verdi
    </w>
    <w>
     .
    </w>
   </s>
   <s>
    <w>
     «
    </w>
    <w>
     Hør
    </w>
    <w>
     her
    </w>
    <w>
     ,
    </w>
    <w>
     hør
    </w>
    <w>
     her
    </w>
    <w>
     ,
    </w>
    <w>
     vét
    </w>
    <w>
     Di
    </w>
    <w>
     hvad
    </w>
    <w>
     ?
    </w>
   </s>
   <s>
    <w>
     Vét
    </w>
    <w>
     Di
    </w>
    <w>
     hvad
    </w>
    <w>
     ?
    </w>
   </s>
   <s>
    <w>
     Aldri
    </w>
    <w>
     i
    </w>
    <w>
     Verden
    </w>
    <w>
     .
    </w>
   </s>
   <s>
    <w>
     Hør
    </w>
    <w>
     ;
    </w>
    <w>
     vét
    </w>
    <w>
     Di
    </w>
    <w>
     hvad
    </w>
    <w>
     ?
    </w>
   </s>
  </p>
  <p n="NOR0013885">
   <s>
    <w>
     Gabriel
    </w>
    <w>
     Gram
    </w>
    <w>
     viste
    </w>
    <w>
     seg
    </w>
    <w>
     ;
    </w>
    <w>
     han
    </w>
    <w>
     var
    </w>
    <w>
     noko
    </w>
    <w>
     fløven
    </w>
    <w>
     aa
    </w>
    <w>
     sjaa
    </w>
    <w>
     til
    </w>
    <w>
     ;
    </w>
    <w>
     eit
    </w>
    <w>
     Grand
    </w>
    <w>
     ustød
    </w>
    <w>
     ,
    </w>
    <w>
     og
    </w>
    <w>
     heller
    </w>
    <w>
     bleik
    </w>
    <w>
     .
    </w>
   </s>
   <s>
    <w>
     Han
    </w>
    <w>
     tok
    </w>
    <w>
     Georg
    </w>
    <w>
     i
    </w>
    <w>
     Armen
    </w>
    <w>
     og
    </w>
    <w>
     bad
    </w>
    <w>
     han
    </w>
    <w>
     fylgje
    </w>
    <w>
     med
    </w>
    <w>
     inn
    </w>
    <w>
     i
    </w>
    <w>
     Piano-rome
    </w>
    <w>
     .
    </w>
   </s>
   <s>
    <w>
     Georg
    </w>
    <w>
     fylgde
    </w>
    <w>
     .
    </w>
   </s>
  </p>
  <p n="NOR0013886">
   <s>
    <w>
     Det
    </w>
    <w>
     vesle
    </w>
    <w>
     Pianorome
    </w>
    <w>
     var
    </w>
    <w>
     fullt
    </w>
    <w>
     av
    </w>
    <w>
     Folk
    </w>
    <w>
     og
    </w>
    <w>
     Tobaksrøyk
    </w>
    <w>
     .
    </w>
   </s>
   <s>
    <w>
     I
    </w>
    <w>
     Sofaen
    </w>
    <w>
     sat
    </w>
    <w>
     ein
    </w>
    <w>
     eldre
    </w>
    <w>
     Herre
    </w>
    <w>
     med
    </w>
    <w>
     bleikt
    </w>
    <w>
     Aasyn
    </w>
    <w>
     og
    </w>
    <w>
     svarte
    </w>
    <w>
     Lokkar
    </w>
    <w>
     og
    </w>
    <w>
     tala
    </w>
    <w>
     ,
    </w>
    <w>
     endaa
    </w>
    <w>
     ingin
    </w>
    <w>
     høyrde
    </w>
    <w>
     paa'n
    </w>
    <w>
     ;
    </w>
    <w>
     dei
    </w>
    <w>
     kundekonversere
    </w>
    <w>
     dei
    </w>
    <w>
     gamle
    </w>
    <w>
     ,
    </w>
    <w>
     sa
    </w>
    <w>
     han
    </w>
    <w>
     ;
    </w>
    <w>
     dei
    </w>
    <w>
     hadde
    </w>
    <w>
     Konversasjon
    </w>
    <w>
     ;
    </w>
    <w>
     me
    </w>
    <w>
     kunde
    </w>
    <w>
     berre
    </w>
    <w>
     disputere
    </w>
    <w>
     og
    </w>
    <w>
     halde
    </w>
    <w>
     Foredrag
    </w>
    <w>
     .
    </w>
   </s>
   <s>
    <w>
     Den
    </w>
    <w>
     gamle
    </w>
    <w>
     dansk-tyske
    </w>
    <w>
     Kulturen
    </w>
    <w>
     døydde
    </w>
    <w>
     ut
    </w>
    <w>
     ;
    </w>
    <w>
     dei
    </w>
    <w>
     Folk
    </w>
    <w>
     me
    </w>
    <w>
     no
    </w>
    <w>
     hadde
    </w>
    <w>
     ,
    </w>
    <w>
     var
    </w>
    <w>
     Uppkomingar
    </w>
    <w>
     ,
    </w>
    <w>
     Grosserarar
    </w>
    <w>
     ,
    </w>
    <w>
     «
    </w>
    <w>
     Halvfinhet
    </w>
    <w>
     med
    </w>
    <w>
     Prætangsjoner
    </w>
    <w>
     »
    </w>
    <w>
     .
    </w>
   </s>
   <s>
    <w>
     So
    </w>
    <w>
     var
    </w>
    <w>
     daa
    </w>
    <w>
     og
    </w>
    <w>
     Intelligensen
    </w>
    <w>
     servil
    </w>
    <w>
     ;
    </w>
    <w>
     alt
    </w>
    <w>
     halvfint
    </w>
    <w>
     var
    </w>
    <w>
     servilt
    </w>
    <w>
     .
    </w>
   </s>
   <s>
    <w>
     Dei
    </w>
    <w>
     gamle
    </w>
    <w>
     kunde
    </w>
    <w>
     bøygje
    </w>
    <w>
     Rygg
    </w>
    <w>
     dei
    </w>
    <w>
     ,
    </w>
    <w>
     men
    </w>
    <w>
     var
    </w>
    <w>
     like
    </w>
    <w>
     stive
    </w>
    <w>
     i
    </w>
    <w>
     Karakteren
    </w>
    <w>
     ;
    </w>
    <w>
     slo
    </w>
    <w>
     Hs
    </w>
    <w>
     .
    </w>
   </s>
   <s>
    <w>
     Maj
    </w>
    <w>
     .
    </w>
   </s>
   <s>
    <w>
     Kongen
    </w>
    <w>
     Hatten
    </w>
    <w>
     av
    </w>
    <w>
     Statsraaden
    </w>
    <w>
     sin
    </w>
    <w>
     ,
    </w>
    <w>
     so
    </w>
    <w>
     maatte
    </w>
    <w>
     so
    </w>
    <w>
     pinedød
    </w>
    <w>
     Hs
    </w>
    <w>
     .
    </w>
   </s>
   <s>
    <w>
     Maj
    </w>
    <w>
     .
    </w>
   </s>
   <s>
    <w>
     sjølv
    </w>
    <w>
     bøygje
    </w>
    <w>
     seg
    </w>
    <w>
     ned
    </w>
    <w>
     og
    </w>
    <w>
     taka
    </w>
    <w>
     Hatten
    </w>
    <w>
     upp
    </w>
    <w>
     att
    </w>
    <w>
     ;
    </w>
    <w>
     men
    </w>
    <w>
     no
    </w>
    <w>
     laag
    </w>
    <w>
     dei
    </w>
    <w>
     fine
    </w>
    <w>
     paa
    </w>
    <w>
     Kne
    </w>
    <w>
     og
    </w>
    <w>
     bad
    </w>
    <w>
     Hs
    </w>
    <w>
     .
    </w>
   </s>
   <s>
    <w>
     Maj
    </w>
    <w>
     .
    </w>
   </s>
   <s>
    <w>
     «
    </w>
    <w>
     naadigst
    </w>
    <w>
     »
    </w>
    <w>
     binde
    </w>
    <w>
     Hendar
    </w>
    <w>
     og
    </w>
    <w>
     Føter
    </w>
    <w>
     paa
    </w>
    <w>
     oss
    </w>
    <w>
     med
    </w>
    <w>
     eit
    </w>
    <w>
     absolut
    </w>
    <w>
     Veto
    </w>
    <w>
     .
    </w>
   </s>
  </p>
  <p n="NOR0013887">
   <s>
    <w>
     Lage
    </w>
    <w>
     hadde
    </w>
    <w>
     skilt
    </w>
    <w>
     seg
    </w>
    <w>
     sund
    </w>
    <w>
     i
    </w>
    <w>
     Smaahopar
    </w>
    <w>
     ;
    </w>
    <w>
     Folk
    </w>
    <w>
     gjekk
    </w>
    <w>
     og
    </w>
    <w>
     kom
    </w>
    <w>
     ;
    </w>
    <w>
     yvi
    </w>
    <w>
     det
    </w>
    <w>
     heile
    </w>
    <w>
     laag
    </w>
    <w>
     Tobaksrøyken
    </w>
    <w>
     som
    </w>
    <w>
     eit
    </w>
    <w>
     tett
    </w>
    <w>
     Draumslør
    </w>
    <w>
     .
    </w>
   </s>
   <s>
    <w>
     Ved
    </w>
    <w>
     Pianoe
    </w>
    <w>
     sat
    </w>
    <w>
     ein
    </w>
    <w>
     høg
    </w>
    <w>
     ,
    </w>
    <w>
     ven
    </w>
    <w>
     Gut
    </w>
    <w>
     og
    </w>
    <w>
     spéla
    </w>
    <w>
     ;
    </w>
    <w>
     for
    </w>
    <w>
     den
    </w>
    <w>
     nedre
    </w>
    <w>
     Bordenden
    </w>
    <w>
     sat
    </w>
    <w>
     tvo
    </w>
    <w>
     unge
    </w>
    <w>
     Fyrar
    </w>
    <w>
     og
    </w>
    <w>
     gjorde
    </w>
    <w>
     Kattemusik
    </w>
    <w>
     :
    </w>
    <w>
     «
    </w>
    <w>
     mjau
    </w>
    <w>
     !
    </w>
   </s>
   <s>
    <w>
     mjau
    </w>
    <w>
     !
    </w>
    <w>
     »
    </w>
    <w>
     men
    </w>
    <w>
     inn-imillom
    </w>
    <w>
     sagde
    </w>
    <w>
     den
    </w>
    <w>
     eine
    </w>
    <w>
     av
    </w>
    <w>
     deim
    </w>
    <w>
     med
    </w>
    <w>
     halv-dansk
    </w>
    <w>
     Ut-tale
    </w>
    <w>
     :
    </w>
    <w>
     «
    </w>
    <w>
     vil
    </w>
    <w>
     du
    </w>
    <w>
     prøve
    </w>
    <w>
     Kærligheden
    </w>
    <w>
     .
    </w>
    <w>
     »
    </w>
    <w>
     Ein
    </w>
    <w>
     og
    </w>
    <w>
     annan
    </w>
    <w>
     reiste
    </w>
    <w>
     seg
    </w>
    <w>
     og
    </w>
    <w>
     heldt
    </w>
    <w>
     Tale
    </w>
    <w>
     ;
    </w>
    <w>
     det
    </w>
    <w>
     vart
    </w>
    <w>
     sagt
    </w>
    <w>
     Bravo
    </w>
    <w>
     kvar
    </w>
    <w>
     Gong
    </w>
    <w>
     dei
    </w>
    <w>
     gjorde
    </w>
    <w>
     ein
    </w>
    <w>
     Stans
    </w>
    <w>
     .
    </w>
   </s>
   <s>
    <w>
     Ein
    </w>
    <w>
     ung
    </w>
    <w>
     Gut
    </w>
    <w>
     tala
    </w>
    <w>
     for
    </w>
    <w>
     Kvinna
    </w>
    <w>
     ;
    </w>
    <w>
     Skaal
    </w>
    <w>
     for
    </w>
    <w>
     at
    </w>
    <w>
     Kvinna
    </w>
    <w>
     maatte
    </w>
    <w>
     forstaa
    </w>
    <w>
     oss
    </w>
    <w>
     !
    </w>
   </s>
   <s>
    <w>
     Georg
    </w>
    <w>
     Jonathan
    </w>
    <w>
     sagde
    </w>
    <w>
     med
    </w>
    <w>
     eit
    </w>
    <w>
     høgt
    </w>
    <w>
     ,
    </w>
    <w>
     skarpt
    </w>
    <w>
     Maal
    </w>
    <w>
     som
    </w>
    <w>
     vart
    </w>
    <w>
     høyrt
    </w>
    <w>
     :
    </w>
    <w>
     ho
    </w>
    <w>
     vilde
    </w>
    <w>
     lære
    </w>
    <w>
     aa
    </w>
    <w>
     forstaa
    </w>
    <w>
     oss
    </w>
    <w>
     ,
    </w>
    <w>
     dersom
    </w>
    <w>
     ho
    </w>
    <w>
     var
    </w>
    <w>
     her
    </w>
    <w>
     !
    </w>
   </s>
   <s>
    <w>
     «
    </w>
    <w>
     Nei
    </w>
    <w>
     !
    </w>
   </s>
  </p>
 </sample>
 <sample>
  <p n="NOR0013419">
   <s>
    <w>
     Eller
    </w>
    <w>
     ho
    </w>
    <w>
     slo
    </w>
    <w>
     seg
    </w>
    <w>
     vill
    </w>
    <w>
     .
    </w>
   </s>
   <s>
    <w>
     Tumla
    </w>
    <w>
     med
    </w>
    <w>
     Studenten
    </w>
    <w>
     meir
    </w>
    <w>
     enn
    </w>
    <w>
     maateleg
    </w>
    <w>
     ;
    </w>
    <w>
     bar
    </w>
    <w>
     seg
    </w>
    <w>
     aat
    </w>
    <w>
     som
    </w>
    <w>
     eit
    </w>
    <w>
     Uting
    </w>
    <w>
     ;
    </w>
    <w>
     for
    </w>
    <w>
     no
    </w>
    <w>
     kunde
    </w>
    <w>
     det
    </w>
    <w>
     ikkje
    </w>
    <w>
     bli
    </w>
    <w>
     stort
    </w>
    <w>
     verre
    </w>
    <w>
     enn
    </w>
    <w>
     det
    </w>
    <w>
     var
    </w>
    <w>
     .
    </w>
   </s>
  </p>
  <p n="NOR0013420">
   <s>
    <w>
     Men
    </w>
    <w>
     hadde
    </w>
    <w>
     ho
    </w>
    <w>
     ikkje
    </w>
    <w>
     anna
    </w>
    <w>
     aa
    </w>
    <w>
     ottast
    </w>
    <w>
     fyri
    </w>
    <w>
     ,
    </w>
    <w>
     so
    </w>
    <w>
     hadde
    </w>
    <w>
     ho
    </w>
    <w>
     Husbondsfolke
    </w>
    <w>
     sitt
    </w>
    <w>
     .
    </w>
   </s>
   <s>
    <w>
     Ho
    </w>
    <w>
     hadde
    </w>
    <w>
     ikkje
    </w>
    <w>
     høyrt
    </w>
    <w>
     meir
    </w>
    <w>
     sidan
    </w>
    <w>
     hin
    </w>
    <w>
     Gongen
    </w>
    <w>
     innpaa
    </w>
    <w>
     Kantore
    </w>
    <w>
     ;
    </w>
    <w>
     men
    </w>
    <w>
     det
    </w>
    <w>
     kom
    </w>
    <w>
     nok
    </w>
    <w>
     .
    </w>
   </s>
   <s>
    <w>
     Kandidaten
    </w>
    <w>
     var
    </w>
    <w>
     snild
    </w>
    <w>
     ;
    </w>
    <w>
     han
    </w>
    <w>
     vart
    </w>
    <w>
     blid
    </w>
    <w>
     som
    </w>
    <w>
     ei
    </w>
    <w>
     Leike
    </w>
    <w>
     berre
    </w>
    <w>
     ein
    </w>
    <w>
     gav
    </w>
    <w>
     han
    </w>
    <w>
     ein
    </w>
    <w>
     Kopp
    </w>
    <w>
     Kaffi
    </w>
    <w>
     .
    </w>
   </s>
   <s>
    <w>
     Men
    </w>
    <w>
     Frua
    </w>
    <w>
     ?
    </w>
   </s>
   <s>
    <w>
     Uff
    </w>
    <w>
     .
    </w>
   </s>
  </p>
  <p n="NOR0013421">
   <s>
    <w>
     Stundom
    </w>
    <w>
     ,
    </w>
    <w>
     naar
    </w>
    <w>
     Studenten
    </w>
    <w>
     hadde
    </w>
    <w>
     vori
    </w>
    <w>
     seint
    </w>
    <w>
     ute
    </w>
    <w>
     um
    </w>
    <w>
     Kvelden
    </w>
    <w>
     ,
    </w>
    <w>
     kunde
    </w>
    <w>
     ho
    </w>
    <w>
     høyre
    </w>
    <w>
     Kandidaten
    </w>
    <w>
     spyrja
    </w>
    <w>
     Frua
    </w>
    <w>
     ,
    </w>
    <w>
     um
    </w>
    <w>
     dei
    </w>
    <w>
     skulde
    </w>
    <w>
     tala
    </w>
    <w>
     til
    </w>
    <w>
     han
    </w>
    <w>
     .
    </w>
   </s>
   <s>
    <w>
     «
    </w>
    <w>
     Du
    </w>
    <w>
     vèt
    </w>
    <w>
     vi
    </w>
    <w>
     har
    </w>
    <w>
     Ansvar
    </w>
    <w>
     overfor
    </w>
    <w>
     Pastor
    </w>
    <w>
     Broch
    </w>
    <w>
     ,
    </w>
    <w>
     »
    </w>
    <w>
     sa
    </w>
    <w>
     han
    </w>
    <w>
     .
    </w>
   </s>
   <s>
    <w>
     Daa
    </w>
    <w>
     tenkte
    </w>
    <w>
     Helene
    </w>
    <w>
     so
    </w>
    <w>
     mangt
    </w>
    <w>
     med
    </w>
    <w>
     seg
    </w>
    <w>
     ;
    </w>
    <w>
     stundom
    </w>
    <w>
     lo
    </w>
    <w>
     ho
    </w>
    <w>
     ,
    </w>
    <w>
     men
    </w>
    <w>
     stundom
    </w>
    <w>
     fekk
    </w>
    <w>
     ho
    </w>
    <w>
     Skjelte
    </w>
    <w>
     .
    </w>
   </s>
  </p>
  <p n="NOR0013422"/>
  <p n="NOR0013423"/>
  <p n="NOR0013424">
   <s>
    <w>
     Det
    </w>
    <w>
     var
    </w>
    <w>
     Moro
    </w>
    <w>
     der
    </w>
    <w>
     Mark
    </w>
    <w>
     Oliv
    </w>
    <w>
     vanka
    </w>
    <w>
     ,
    </w>
    <w>
     Laatt
    </w>
    <w>
     og
    </w>
    <w>
     Staak
    </w>
    <w>
     og
    </w>
    <w>
     Huse
    </w>
    <w>
     paa
    </w>
    <w>
     Ende
    </w>
    <w>
     ;
    </w>
    <w>
     og
    </w>
    <w>
     likevel
    </w>
    <w>
     var
    </w>
    <w>
     Mark
    </w>
    <w>
     Oliv
    </w>
    <w>
     ein
    </w>
    <w>
     aalvorsam
    </w>
    <w>
     Mann
    </w>
    <w>
     .
    </w>
   </s>
  </p>
  <p n="NOR0013425">
   <s>
    <w>
     Det
    </w>
    <w>
     var
    </w>
    <w>
     han
    </w>
    <w>
     daa
    </w>
    <w>
     og
    </w>
    <w>
     fraa
    </w>
    <w>
     Morgo
    </w>
    <w>
     til
    </w>
    <w>
     Kveld
    </w>
    <w>
     ,
    </w>
    <w>
     ute
    </w>
    <w>
     og
    </w>
    <w>
     inne
    </w>
    <w>
     ,
    </w>
    <w>
     paa
    </w>
    <w>
     Gata
    </w>
    <w>
     og
    </w>
    <w>
     paa
    </w>
    <w>
     Kantore
    </w>
    <w>
     .
    </w>
   </s>
  </p>
  <p n="NOR0013426">
   <s>
    <w>
     Han
    </w>
    <w>
     hadde
    </w>
    <w>
     eit
    </w>
    <w>
     nytt
    </w>
    <w>
     Evangelium
    </w>
    <w>
     i
    </w>
    <w>
     Kveld
    </w>
    <w>
     :
    </w>
    <w>
     Folk
    </w>
    <w>
     skulde
    </w>
    <w>
     lære
    </w>
    <w>
     seg
    </w>
    <w>
     til
    </w>
    <w>
     aa
    </w>
    <w>
     eta
    </w>
    <w>
     Skjeljar
    </w>
    <w>
     .
    </w>
   </s>
   <s>
    <w>
     Han
    </w>
    <w>
     hadde
    </w>
    <w>
     funni
    </w>
    <w>
     ut
    </w>
    <w>
     at
    </w>
    <w>
     Norig
    </w>
    <w>
     kunde
    </w>
    <w>
     vera
    </w>
    <w>
     eit
    </w>
    <w>
     rikt
    </w>
    <w>
     Land
    </w>
    <w>
     ,
    </w>
    <w>
     og
    </w>
    <w>
     br-
    </w>
    <w>
     braudføde
    </w>
    <w>
     ,
    </w>
    <w>
     ha
    </w>
    <w>
     !
    </w>
   </s>
   <s>
    <w>
     ha
    </w>
    <w>
     !
    </w>
   </s>
   <s>
    <w>
     ha
    </w>
    <w>
     !
    </w>
   </s>
   <s>
    <w>
     braudføde
    </w>
    <w>
     dùbbelt
    </w>
    <w>
     so
    </w>
    <w>
     mange
    </w>
    <w>
     Ibuarar
    </w>
    <w>
     (
    </w>
    <w>
     Mark
    </w>
    <w>
     Oliv
    </w>
    <w>
     tala
    </w>
    <w>
     Landsmaal
    </w>
    <w>
     ,
    </w>
    <w>
     naar
    </w>
    <w>
     det
    </w>
    <w>
     skulde
    </w>
    <w>
     vera
    </w>
    <w>
     gildt
    </w>
    <w>
     )
    </w>
    <w>
     ,
    </w>
    <w>
     dersom
    </w>
    <w>
     berre
    </w>
    <w>
     Folk
    </w>
    <w>
     frametter
    </w>
    <w>
     Havstrendane
    </w>
    <w>
     vilde
    </w>
    <w>
     stelle
    </w>
    <w>
     seg
    </w>
    <w>
     som
    </w>
    <w>
     dei
    </w>
    <w>
     skulde
    </w>
    <w>
     med
    </w>
    <w>
     Skjeljane
    </w>
    <w>
     .
    </w>
   </s>
   <s>
    <w>
     Det
    </w>
    <w>
     var
    </w>
    <w>
     ei
    </w>
    <w>
     Nasjonalsak
    </w>
    <w>
     .
    </w>
   </s>
   <s>
    <w>
     Og
    </w>
    <w>
     Skjeljar
    </w>
    <w>
     var
    </w>
    <w>
     god
    </w>
    <w>
     Mat
    </w>
    <w>
     ,
    </w>
    <w>
     fin
    </w>
    <w>
     Mat
    </w>
    <w>
     ;
    </w>
    <w>
     Franskmennane
    </w>
    <w>
     aat
    </w>
    <w>
     Skjeljar
    </w>
    <w>
     i
    </w>
    <w>
     Haugevis
    </w>
    <w>
     ;
    </w>
    <w>
     han
    </w>
    <w>
     hadde
    </w>
    <w>
     sjølv
    </w>
    <w>
     eti
    </w>
    <w>
     Skjeljar
    </w>
    <w>
     .
    </w>
   </s>
   <s>
    <w>
     Helga
    </w>
    <w>
     ,
    </w>
    <w>
     Husfruva
    </w>
    <w>
     hans
    </w>
    <w>
     ,
    </w>
    <w>
     skulde
    </w>
    <w>
     lære
    </w>
    <w>
     aa
    </w>
    <w>
     laga
    </w>
    <w>
     deim
    </w>
    <w>
     no
    </w>
    <w>
     ;
    </w>
    <w>
     og
    </w>
    <w>
     so
    </w>
    <w>
     skulde
    </w>
    <w>
     dei
    </w>
    <w>
     Ærade
    </w>
    <w>
     Damur
    </w>
    <w>
     og
    </w>
    <w>
     Herrar
    </w>
    <w>
     ,
    </w>
    <w>
     dersom
    </w>
    <w>
     dei
    </w>
    <w>
     vilde
    </w>
    <w>
     daa
    </w>
    <w>
     –
    </w>
    <w>
     og
    </w>
    <w>
     det
    </w>
    <w>
     vilde
    </w>
    <w>
     dei
    </w>
    <w>
     hoffentlich
    </w>
    <w>
     ,
    </w>
    <w>
     for
    </w>
    <w>
     det
    </w>
    <w>
     var
    </w>
    <w>
     ei
    </w>
    <w>
     nasjonal
    </w>
    <w>
     Sak
    </w>
    <w>
     –
    </w>
    <w>
     ,
    </w>
    <w>
     faa
    </w>
    <w>
     seg
    </w>
    <w>
     ein
    </w>
    <w>
     Seksa
    </w>
    <w>
     paa
    </w>
    <w>
     Skjeljar
    </w>
    <w>
     i
    </w>
    <w>
     hans
    </w>
    <w>
     ibuande
    </w>
    <w>
     men
    </w>
    <w>
     ikkje
    </w>
    <w>
     eigande
    </w>
    <w>
     Hus
    </w>
    <w>
     Tollbugata
    </w>
    <w>
     Nummer
    </w>
    <w>
     det
    </w>
    <w>
     og
    </w>
    <w>
     det
    </w>
    <w>
     .
    </w>
   </s>
  </p>
 </sample>
 <sample>
  <p n="NOR0013710">
   <s>
    <w>
     Ny
    </w>
    <w>
     Dans
    </w>
    <w>
     .
    </w>
   </s>
  </p>
  <p n="NOR0013711">
   <s>
    <w>
     Det
    </w>
    <w>
     kom
    </w>
    <w>
     Folk
    </w>
    <w>
     inn
    </w>
    <w>
     jamt
    </w>
    <w>
     ;
    </w>
    <w>
     Golve
    </w>
    <w>
     var
    </w>
    <w>
     so
    </w>
    <w>
     fullt
    </w>
    <w>
     at
    </w>
    <w>
     der
    </w>
    <w>
     var
    </w>
    <w>
     lite
    </w>
    <w>
     Rom
    </w>
    <w>
     til
    </w>
    <w>
     aa
    </w>
    <w>
     snu
    </w>
    <w>
     seg
    </w>
    <w>
     .
    </w>
   </s>
   <s>
    <w>
     Rett
    </w>
    <w>
     som
    </w>
    <w>
     det
    </w>
    <w>
     var
    </w>
    <w>
     kom
    </w>
    <w>
     dei
    </w>
    <w>
     upp-i
    </w>
    <w>
     slik
    </w>
    <w>
     ein
    </w>
    <w>
     Krull
    </w>
    <w>
     av
    </w>
    <w>
     Folk
    </w>
    <w>
     ,
    </w>
    <w>
     at
    </w>
    <w>
     dei
    </w>
    <w>
     laut
    </w>
    <w>
     stana
    </w>
    <w>
     .
    </w>
   </s>
   <s>
    <w>
     Som
    </w>
    <w>
     dei
    </w>
    <w>
     heldt
    </w>
    <w>
     paa
    </w>
    <w>
     med
    </w>
    <w>
     aa
    </w>
    <w>
     arbeide
    </w>
    <w>
     seg
    </w>
    <w>
     ut
    </w>
    <w>
     «
    </w>
    <w>
     paa
    </w>
    <w>
     fri
    </w>
    <w>
     Sjø
    </w>
    <w>
     »
    </w>
    <w>
     att
    </w>
    <w>
     ,
    </w>
    <w>
     som
    </w>
    <w>
     Knutzon
    </w>
    <w>
     sa
    </w>
    <w>
     ,
    </w>
    <w>
     kom
    </w>
    <w>
     det
    </w>
    <w>
     ein
    </w>
    <w>
     Konstabel
    </w>
    <w>
     baskande
    </w>
    <w>
     .
    </w>
   </s>
   <s>
    <w>
     «
    </w>
    <w>
     Undskyld
    </w>
    <w>
     De
    </w>
    <w>
     ,
    </w>
    <w>
     sa
    </w>
    <w>
     han
    </w>
    <w>
     .
    </w>
   </s>
   <s>
    <w>
     «
    </w>
    <w>
     Hva
    </w>
    <w>
     behager
    </w>
    <w>
     ?
    </w>
    <w>
     »
    </w>
    <w>
     sa
    </w>
    <w>
     Knutzon
    </w>
    <w>
     ;
    </w>
    <w>
     han
    </w>
    <w>
     vart
    </w>
    <w>
     so
    </w>
    <w>
     bleik
    </w>
    <w>
     og
    </w>
    <w>
     rar
    </w>
    <w>
     .
    </w>
   </s>
   <s>
    <w>
     «
    </w>
    <w>
     Vær
    </w>
    <w>
     rolig
    </w>
    <w>
     Di
    </w>
    <w>
     ,
    </w>
    <w>
     »
    </w>
    <w>
     sa
    </w>
    <w>
     Konstabelen
    </w>
    <w>
     ;
    </w>
    <w>
     «
    </w>
    <w>
     Det
    </w>
    <w>
     er
    </w>
    <w>
     ikke
    </w>
    <w>
     Dere
    </w>
    <w>
     det
    </w>
    <w>
     gjelder
    </w>
    <w>
     denne
    </w>
    <w>
     Gangen
    </w>
    <w>
     .
    </w>
   </s>
   <s>
    <w>
     Det
    </w>
    <w>
     var
    </w>
    <w>
     den
    </w>
    <w>
     Damen
    </w>
    <w>
     der
    </w>
    <w>
     .
    </w>
   </s>
   <s>
    <w>
     Di
    </w>
    <w>
     ?
    </w>
   </s>
   <s>
    <w>
     Jomfru
    </w>
    <w>
     ?
    </w>
   </s>
   <s>
    <w>
     Vil
    </w>
    <w>
     Di
    </w>
    <w>
     være
    </w>
    <w>
     saa
    </w>
    <w>
     god
    </w>
    <w>
     aa
    </w>
    <w>
     oppgji
    </w>
    <w>
     mej
    </w>
    <w>
     Deres
    </w>
    <w>
     Navn
    </w>
    <w>
     ?
    </w>
    <w>
     »
    </w>
    <w>
     Folk
    </w>
    <w>
     stima
    </w>
    <w>
     til
    </w>
    <w>
     ;
    </w>
    <w>
     Knutzon
    </w>
    <w>
     kom
    </w>
    <w>
     burt
    </w>
    <w>
     for
    </w>
    <w>
     Helene
    </w>
    <w>
     .
    </w>
   </s>
   <s>
    <w>
     Daa
    </w>
    <w>
     ho
    </w>
    <w>
     skýna
    </w>
    <w>
     det
    </w>
    <w>
     var
    </w>
    <w>
     henne
    </w>
    <w>
     ,
    </w>
    <w>
     Konstabelen
    </w>
    <w>
     meinte
    </w>
    <w>
     paa
    </w>
    <w>
     ,
    </w>
    <w>
     tok
    </w>
    <w>
     ho
    </w>
    <w>
     til
    </w>
    <w>
     aa
    </w>
    <w>
     skjelve
    </w>
    <w>
     og
    </w>
    <w>
     vilde
    </w>
    <w>
     røme
    </w>
    <w>
     ,
    </w>
    <w>
     men
    </w>
    <w>
     kom
    </w>
    <w>
     ingin
    </w>
    <w>
     Veg
    </w>
    <w>
     .
    </w>
   </s>
   <s>
    <w>
     «
    </w>
    <w>
     Deres
    </w>
    <w>
     Navn
    </w>
    <w>
     ,
    </w>
    <w>
     »
    </w>
    <w>
     sa
    </w>
    <w>
     Konstabelen
    </w>
    <w>
     ;
    </w>
    <w>
     han
    </w>
    <w>
     stod
    </w>
    <w>
     med
    </w>
    <w>
     Boki
    </w>
    <w>
     og
    </w>
    <w>
     Blyanten
    </w>
    <w>
     ferdug
    </w>
    <w>
     .
    </w>
   </s>
   <s>
    <w>
     Daa
    </w>
    <w>
     misste
    </w>
    <w>
     ho
    </w>
    <w>
     Sans
    </w>
    <w>
     og
    </w>
    <w>
     Samling
    </w>
    <w>
     ;
    </w>
    <w>
     ho
    </w>
    <w>
     skrek
    </w>
    <w>
     upp
    </w>
    <w>
     i
    </w>
    <w>
     villan
    </w>
    <w>
     Sky
    </w>
    <w>
     ,
    </w>
    <w>
     kva
    </w>
    <w>
     Konstabelen
    </w>
    <w>
     hadde
    </w>
    <w>
     med
    </w>
    <w>
     henne
    </w>
    <w>
     aa
    </w>
    <w>
     gjera
    </w>
    <w>
     ?
    </w>
   </s>
   <s>
    <w>
     um
    </w>
    <w>
     ho
    </w>
    <w>
     hadde
    </w>
    <w>
     gjort
    </w>
    <w>
     noko
    </w>
    <w>
     vondt
    </w>
    <w>
     ?
    </w>
   </s>
   <s>
    <w>
     Heile
    </w>
    <w>
     Salen
    </w>
    <w>
     tok
    </w>
    <w>
     til
    </w>
    <w>
     aa
    </w>
    <w>
     lyde
    </w>
    <w>
     .
    </w>
   </s>
   <s>
    <w>
     Eit
    </w>
    <w>
     Mannfolkmaal
    </w>
    <w>
     kviskra
    </w>
    <w>
     yvi
    </w>
    <w>
     Aksli
    </w>
    <w>
     til
    </w>
    <w>
     Helene
    </w>
    <w>
     :
    </w>
    <w>
     «
    </w>
    <w>
     d'er
    </w>
    <w>
     'ke
    </w>
    <w>
     farli
    </w>
    <w>
     ,
    </w>
    <w>
     d'er
    </w>
    <w>
     'ke
    </w>
    <w>
     farli
    </w>
    <w>
     ;
    </w>
    <w>
     gje
    </w>
    <w>
     opp
    </w>
    <w>
     Navn
    </w>
    <w>
     og
    </w>
    <w>
     Adresse
    </w>
    <w>
     ,
    </w>
    <w>
     saa
    </w>
    <w>
     er
    </w>
    <w>
     det
    </w>
    <w>
     'ke
    </w>
    <w>
     mer
    </w>
    <w>
     !
    </w>
    <w>
     »
    </w>
    <w>
     men
    </w>
    <w>
     Helene
    </w>
    <w>
     var
    </w>
    <w>
     vitskræmd
    </w>
    <w>
     og
    </w>
    <w>
     samla
    </w>
    <w>
     inginting
    </w>
    <w>
     .
    </w>
   </s>
   <s>
    <w>
     «
    </w>
    <w>
     Di
    </w>
    <w>
     gjør
    </w>
    <w>
     bedst
    </w>
    <w>
     i
    </w>
    <w>
     aa
    </w>
    <w>
     ikke
    </w>
    <w>
     gjøre
    </w>
    <w>
     no
    </w>
    <w>
     '
    </w>
    <w>
     Slags
    </w>
    <w>
     Vrøvl
    </w>
    <w>
     her
    </w>
    <w>
     ,
    </w>
    <w>
     »
    </w>
    <w>
     meinte
    </w>
    <w>
     Konstabelen
    </w>
    <w>
     ;
    </w>
    <w>
     «
    </w>
    <w>
     kom
    </w>
    <w>
     med
    </w>
    <w>
     Navne
    </w>
    <w>
     naa
    </w>
    <w>
     .
    </w>
    <w>
     »
    </w>
    <w>
     «
    </w>
    <w>
     Si
    </w>
    <w>
     det
    </w>
    <w>
     ;
    </w>
    <w>
     si
    </w>
    <w>
     det
    </w>
    <w>
     ;
    </w>
    <w>
     vær
    </w>
    <w>
     ikke
    </w>
    <w>
     dum
    </w>
    <w>
     »
    </w>
    <w>
     kviskra
    </w>
    <w>
     Mannfolkmaale
    </w>
    <w>
     .
    </w>
   </s>
   <s>
    <w>
     Helene
    </w>
    <w>
     visste
    </w>
    <w>
     ikkje
    </w>
    <w>
     lenger
    </w>
    <w>
     kva
    </w>
    <w>
     ho
    </w>
    <w>
     gjorde
    </w>
    <w>
     ;
    </w>
    <w>
     ho
    </w>
    <w>
     gav
    </w>
    <w>
     upp
    </w>
    <w>
     Namne
    </w>
    <w>
     .
    </w>
   </s>
   <s>
    <w>
     No
    </w>
    <w>
     er
    </w>
    <w>
     eg
    </w>
    <w>
     seld
    </w>
    <w>
     ,
    </w>
    <w>
     tenkte
    </w>
    <w>
     ho
    </w>
    <w>
     .
    </w>
   </s>
   <s>
    <w>
     «
    </w>
    <w>
     Adresse
    </w>
    <w>
     ?
    </w>
    <w>
     »
    </w>
    <w>
     den
    </w>
    <w>
     fekk
    </w>
    <w>
     han
    </w>
    <w>
     og
    </w>
    <w>
     .
    </w>
   </s>
  </p>
  <p n="NOR0013712">
   <s>
    <w>
     «
    </w>
    <w>
     Det
    </w>
    <w>
     er
    </w>
    <w>
     ingen
    </w>
    <w>
     Ting
    </w>
    <w>
     ;
    </w>
    <w>
     Di
    </w>
    <w>
     ska
    </w>
    <w>
     ikke
    </w>
    <w>
     bry
    </w>
    <w>
     Dem
    </w>
    <w>
     om
    </w>
    <w>
     det
    </w>
    <w>
     ,
    </w>
    <w>
     »
    </w>
    <w>
     sa
    </w>
    <w>
     Mannfolke
    </w>
    <w>
     no
    </w>
    <w>
     rolegt
    </w>
    <w>
     og
    </w>
    <w>
     trøystande
    </w>
    <w>
     ;
    </w>
    <w>
     han
    </w>
    <w>
     tala
    </w>
    <w>
     litegrand
    </w>
    <w>
     gjenom
    </w>
    <w>
     Nasen
    </w>
    <w>
     .
    </w>
   </s>
   <s>
    <w>
     Ho
    </w>
    <w>
     stirde
    </w>
    <w>
     rundt
    </w>
    <w>
     etter
    </w>
    <w>
     Knutzon
    </w>
    <w>
     ;
    </w>
    <w>
     han
    </w>
    <w>
     var
    </w>
    <w>
     ingin
    </w>
    <w>
     Stad
    </w>
    <w>
     aa
    </w>
    <w>
     sjaa
    </w>
    <w>
     .
    </w>
   </s>
   <s>
    <w>
     «
    </w>
    <w>
     Nei
    </w>
    <w>
     ,
    </w>
    <w>
     Deres
    </w>
    <w>
     Herre
    </w>
    <w>
     er
    </w>
    <w>
     nok
    </w>
    <w>
     forsvunden
    </w>
    <w>
     ,
    </w>
    <w>
     »
    </w>
    <w>
     sa
    </w>
    <w>
     den
    </w>
    <w>
     framande
    </w>
    <w>
     liksom
    </w>
    <w>
     han
    </w>
    <w>
     visste
    </w>
    <w>
     kva
    </w>
    <w>
     ho
    </w>
    <w>
     tenkte
    </w>
    <w>
     ;
    </w>
    <w>
     «
    </w>
    <w>
     vil
    </w>
    <w>
     Di
    </w>
    <w>
     foreløbi
    </w>
    <w>
     ta
    </w>
    <w>
     te
    </w>
    <w>
     Takke
    </w>
    <w>
     med
    </w>
    <w>
     mej
    </w>
    <w>
     ?
    </w>
    <w>
     »
    </w>
    <w>
     Ho
    </w>
    <w>
     kjende
    </w>
    <w>
     ikkje
    </w>
    <w>
     Fyren
    </w>
    <w>
     ;
    </w>
    <w>
     lika
    </w>
    <w>
     han
    </w>
    <w>
     ikkje
    </w>
    <w>
     ;
    </w>
    <w>
     «
    </w>
    <w>
     nei
    </w>
    <w>
     Takk
    </w>
    <w>
     ,
    </w>
    <w>
     nei
    </w>
    <w>
     Takk
    </w>
    <w>
     ;
    </w>
    <w>
     jeg
    </w>
    <w>
     skal
    </w>
    <w>
     gaa
    </w>
    <w>
     ,
    </w>
    <w>
     »
    </w>
    <w>
     sa
    </w>
    <w>
     ho
    </w>
    <w>
     .
    </w>
   </s>
  </p>
  <p n="NOR0013713">
   <s>
    <w>
     Josefine
    </w>
    <w>
     saag
    </w>
    <w>
     ho
    </w>
    <w>
     ikkje
    </w>
    <w>
     noko
    </w>
    <w>
     til
    </w>
    <w>
     .
    </w>
   </s>
   <s>
    <w>
     Fyrr
    </w>
    <w>
     ho
    </w>
    <w>
     visste
    </w>
    <w>
     Ord
    </w>
    <w>
     av
    </w>
    <w>
     var
    </w>
    <w>
     ho
    </w>
    <w>
     ute
    </w>
    <w>
     .
    </w>
   </s>
   <s>
    <w>
     Ho
    </w>
    <w>
     vilde
    </w>
    <w>
     setja
    </w>
    <w>
     til
    </w>
    <w>
     Sprangs
    </w>
    <w>
     ,
    </w>
    <w>
     men
    </w>
    <w>
     saag
    </w>
    <w>
     tvo
    </w>
    <w>
     Konstablar
    </w>
    <w>
     som
    </w>
    <w>
     gjekk
    </w>
    <w>
     der
    </w>
    <w>
     og
    </w>
    <w>
     dreiv
    </w>
    <w>
     ,
    </w>
    <w>
     og
    </w>
    <w>
     torde
    </w>
    <w>
     daa
    </w>
    <w>
     ikkje
    </w>
    <w>
     .
    </w>
   </s>
   <s>
    <w>
     Det
    </w>
    <w>
     verste
    </w>
    <w>
     var
    </w>
    <w>
     ,
    </w>
    <w>
     at
    </w>
    <w>
     ho
    </w>
    <w>
     skalv
    </w>
    <w>
     so
    </w>
    <w>
     .
    </w>
   </s>
  </p>
 </sample>
 <sample>
  <p n="NOR0013463">
   <s>
    <w>
     Det
    </w>
    <w>
     saag
    </w>
    <w>
     ut
    </w>
    <w>
     som
    </w>
    <w>
     ho
    </w>
    <w>
     visste
    </w>
    <w>
     med
    </w>
    <w>
     seg
    </w>
    <w>
     ,
    </w>
    <w>
     at
    </w>
    <w>
     ingin
    </w>
    <w>
     kunde
    </w>
    <w>
     koma
    </w>
    <w>
     henne
    </w>
    <w>
     nærare
    </w>
    <w>
     enn
    </w>
    <w>
     ho
    </w>
    <w>
     sjølv
    </w>
    <w>
     vilde
    </w>
    <w>
     .
    </w>
   </s>
   <s>
    <w>
     Daa
    </w>
    <w>
     Georg
    </w>
    <w>
     tok
    </w>
    <w>
     til
    </w>
    <w>
     aa
    </w>
    <w>
     tala
    </w>
    <w>
     med
    </w>
    <w>
     henne
    </w>
    <w>
     um
    </w>
    <w>
     Kjærleik
    </w>
    <w>
     ,
    </w>
    <w>
     vart
    </w>
    <w>
     ho
    </w>
    <w>
     korkje
    </w>
    <w>
     glad
    </w>
    <w>
     eller
    </w>
    <w>
     harm
    </w>
    <w>
     ,
    </w>
    <w>
     ikkje
    </w>
    <w>
     raud
    </w>
    <w>
     dessmeir
    </w>
    <w>
     .
    </w>
   </s>
  </p>
  <p n="NOR0013464">
   <s>
    <w>
     Det
    </w>
    <w>
     var
    </w>
    <w>
     ikkje
    </w>
    <w>
     godt
    </w>
    <w>
     for
    </w>
    <w>
     ei
    </w>
    <w>
     Gjente
    </w>
    <w>
     som
    </w>
    <w>
     henne
    </w>
    <w>
     ,
    </w>
    <w>
     sa
    </w>
    <w>
     ho
    </w>
    <w>
     ,
    </w>
    <w>
     aa
    </w>
    <w>
     faa
    </w>
    <w>
     ein
    </w>
    <w>
     Mann
    </w>
    <w>
     som
    </w>
    <w>
     ein
    </w>
    <w>
     kunde
    </w>
    <w>
     vera
    </w>
    <w>
     tent
    </w>
    <w>
     med
    </w>
    <w>
     .
    </w>
    <w>
     Og
    </w>
    <w>
     kasta
    </w>
    <w>
     seg
    </w>
    <w>
     burt
    </w>
    <w>
     var
    </w>
    <w>
     vondt
    </w>
    <w>
     det
    </w>
    <w>
     og
    </w>
    <w>
     .
    </w>
   </s>
   <s>
    <w>
     Ho
    </w>
    <w>
     kunde
    </w>
    <w>
     ikkje
    </w>
    <w>
     ha
    </w>
    <w>
     noko
    </w>
    <w>
     imot
    </w>
    <w>
     aa
    </w>
    <w>
     ha
    </w>
    <w>
     ein
    </w>
    <w>
     Vén
    </w>
    <w>
     ,
    </w>
    <w>
     som
    </w>
    <w>
     ho
    </w>
    <w>
     kunde
    </w>
    <w>
     stole
    </w>
    <w>
     paa
    </w>
    <w>
     ;
    </w>
    <w>
     men
    </w>
    <w>
     Herrane
    </w>
    <w>
     var
    </w>
    <w>
     lite
    </w>
    <w>
     sætande
    </w>
    <w>
     .
    </w>
   </s>
   <s>
    <w>
     Rett
    </w>
    <w>
     som
    </w>
    <w>
     det
    </w>
    <w>
     var
    </w>
    <w>
     gjekk
    </w>
    <w>
     dei
    </w>
    <w>
     til
    </w>
    <w>
     andre
    </w>
    <w>
     ;
    </w>
    <w>
     og
    </w>
    <w>
     um
    </w>
    <w>
     dei
    </w>
    <w>
     so
    </w>
    <w>
     kom
    </w>
    <w>
     att
    </w>
    <w>
     ,
    </w>
    <w>
     kunde
    </w>
    <w>
     det
    </w>
    <w>
     vera
    </w>
    <w>
     Ugreidur
    </w>
    <w>
     .
    </w>
   </s>
  </p>
  <p n="NOR0013465">
   <s>
    <w>
     Han
    </w>
    <w>
     forklaara
    </w>
    <w>
     kva
    </w>
    <w>
     det
    </w>
    <w>
     var
    </w>
    <w>
     han
    </w>
    <w>
     meinte
    </w>
    <w>
     og
    </w>
    <w>
     vilde
    </w>
    <w>
     ;
    </w>
    <w>
     ho
    </w>
    <w>
     svara
    </w>
    <w>
     at
    </w>
    <w>
     dei
    </w>
    <w>
     sa
    </w>
    <w>
     vel
    </w>
    <w>
     nokorlunde
    </w>
    <w>
     det
    </w>
    <w>
     same
    </w>
    <w>
     alle
    </w>
    <w>
     ;
    </w>
    <w>
     men
    </w>
    <w>
     ho
    </w>
    <w>
     skulde
    </w>
    <w>
     tenkje
    </w>
    <w>
     paa
    </w>
    <w>
     det
    </w>
    <w>
     ,
    </w>
    <w>
     sa
    </w>
    <w>
     ho
    </w>
    <w>
     ;
    </w>
    <w>
     og
    </w>
    <w>
     han
    </w>
    <w>
     saag
    </w>
    <w>
     for
    </w>
    <w>
     fyrste
    </w>
    <w>
     Gongen
    </w>
    <w>
     ein
    </w>
    <w>
     varmara
    </w>
    <w>
     Glimt
    </w>
    <w>
     i
    </w>
    <w>
     dei
    </w>
    <w>
     rolege
    </w>
    <w>
     Augo
    </w>
    <w>
     .
    </w>
   </s>
  </p>
  <p n="NOR0013466">
   <s>
    <w>
     Det
    </w>
    <w>
     var
    </w>
    <w>
     elles
    </w>
    <w>
     ikkje
    </w>
    <w>
     so
    </w>
    <w>
     reint
    </w>
    <w>
     vondt
    </w>
    <w>
     for
    </w>
    <w>
     henne
    </w>
    <w>
     no
    </w>
    <w>
     ,
    </w>
    <w>
     so
    </w>
    <w>
     dersom
    </w>
    <w>
     han
    </w>
    <w>
     ikkje
    </w>
    <w>
     kunde
    </w>
    <w>
     lova
    </w>
    <w>
     aa
    </w>
    <w>
     vera
    </w>
    <w>
     snild
    </w>
    <w>
     og
    </w>
    <w>
     reel
    </w>
    <w>
     mot
    </w>
    <w>
     henne
    </w>
    <w>
     ,
    </w>
    <w>
     so
    </w>
    <w>
     skulde
    </w>
    <w>
     han
    </w>
    <w>
     heller
    </w>
    <w>
     lata
    </w>
    <w>
     henne
    </w>
    <w>
     vera
    </w>
    <w>
     .
    </w>
   </s>
   <s>
    <w>
     Ho
    </w>
    <w>
     hadde
    </w>
    <w>
     daa
    </w>
    <w>
     Maten
    </w>
    <w>
     paa
    </w>
    <w>
     ei
    </w>
    <w>
     Vis
    </w>
    <w>
     ;
    </w>
    <w>
     verre
    </w>
    <w>
     var
    </w>
    <w>
     det
    </w>
    <w>
     med
    </w>
    <w>
     Klædi
    </w>
    <w>
     .
    </w>
   </s>
   <s>
    <w>
     Dei
    </w>
    <w>
     andre
    </w>
    <w>
     der
    </w>
    <w>
     nede
    </w>
    <w>
     gjekk
    </w>
    <w>
     som
    </w>
    <w>
     Damur
    </w>
    <w>
     for
    </w>
    <w>
     det
    </w>
    <w>
     meste
    </w>
    <w>
     .
    </w>
   </s>
   <s>
    <w>
     Dei
    </w>
    <w>
     fekk
    </w>
    <w>
     nok
    </w>
    <w>
     ikkje
    </w>
    <w>
     det
    </w>
    <w>
     for
    </w>
    <w>
     ingenting
    </w>
    <w>
     ;
    </w>
    <w>
     men
    </w>
    <w>
     det
    </w>
    <w>
     var
    </w>
    <w>
     vondt
    </w>
    <w>
     aa
    </w>
    <w>
     sjaa
    </w>
    <w>
     altfor
    </w>
    <w>
     simpel
    </w>
    <w>
     ut
    </w>
    <w>
     og
    </w>
    <w>
     .
    </w>
   </s>
   <s>
    <w>
     Ein
    </w>
    <w>
     visste
    </w>
    <w>
     mang
    </w>
    <w>
     ein
    </w>
    <w>
     Gong
    </w>
    <w>
     ikkje
    </w>
    <w>
     kva
    </w>
    <w>
     ein
    </w>
    <w>
     skulde
    </w>
    <w>
     gjera
    </w>
    <w>
     .
    </w>
   </s>
   <s>
    <w>
     Men
    </w>
    <w>
     ho
    </w>
    <w>
     skulde
    </w>
    <w>
     vel
    </w>
    <w>
     koma
    </w>
    <w>
     utav
    </w>
    <w>
     det
    </w>
    <w>
     .
    </w>
   </s>
   <s>
    <w>
     Naar
    </w>
    <w>
     ein
    </w>
    <w>
     kunde
    </w>
    <w>
     gjera
    </w>
    <w>
     alt
    </w>
    <w>
     sjølv
    </w>
    <w>
     ,
    </w>
    <w>
     greidde
    </w>
    <w>
     ein
    </w>
    <w>
     seg
    </w>
    <w>
     utruleg
    </w>
    <w>
     .
    </w>
   </s>
   <s>
    <w>
     Difor
    </w>
    <w>
     skulde
    </w>
    <w>
     han
    </w>
    <w>
     tenkje
    </w>
    <w>
     paa
    </w>
    <w>
     ,
    </w>
    <w>
     um
    </w>
    <w>
     han
    </w>
    <w>
     ikkje
    </w>
    <w>
     gjorde
    </w>
    <w>
     best
    </w>
    <w>
     i
    </w>
    <w>
     aa
    </w>
    <w>
     lata
    </w>
    <w>
     henne
    </w>
    <w>
     vera
    </w>
    <w>
     .
    </w>
   </s>
   <s>
    <w>
     Det
    </w>
    <w>
     var
    </w>
    <w>
     Gjentur
    </w>
    <w>
     nok
    </w>
    <w>
     .
    </w>
   </s>
  </p>
  <p n="NOR0013467">
   <s>
    <w>
     Georg
    </w>
    <w>
     fekk
    </w>
    <w>
     god
    </w>
    <w>
     Tru
    </w>
    <w>
     til
    </w>
    <w>
     Gjenta
    </w>
    <w>
     ;
    </w>
    <w>
     her
    </w>
    <w>
     var
    </w>
    <w>
     ikkje
    </w>
    <w>
     noko
    </w>
    <w>
     Tøv
    </w>
    <w>
     her
    </w>
    <w>
     .
    </w>
   </s>
   <s>
    <w>
     Han
    </w>
    <w>
     saag
    </w>
    <w>
     henne
    </w>
    <w>
     i
    </w>
    <w>
     Augo
    </w>
    <w>
     og
    </w>
    <w>
     sa
    </w>
    <w>
     :
    </w>
    <w>
     «
    </w>
    <w>
     Di
    </w>
    <w>
     skal
    </w>
    <w>
     stole
    </w>
    <w>
     paa
    </w>
    <w>
     mej
    </w>
    <w>
     ,
    </w>
    <w>
     Emilie
    </w>
    <w>
     .
    </w>
   </s>
  </p>
  <p n="NOR0013468">
   <s>
    <w>
     Daa
    </w>
    <w>
     raudna
    </w>
    <w>
     ho
    </w>
    <w>
     eit
    </w>
    <w>
     Grand
    </w>
    <w>
     ;
    </w>
    <w>
     det
    </w>
    <w>
     var
    </w>
    <w>
     visst
    </w>
    <w>
     av
    </w>
    <w>
     Glede
    </w>
    <w>
     .
    </w>
   </s>
   <s>
    <w>
     Aa
    </w>
    <w>
     ja
    </w>
    <w>
     ,
    </w>
    <w>
     ho
    </w>
    <w>
     vilde
    </w>
    <w>
     nok
    </w>
    <w>
     gjerne
    </w>
    <w>
     ha
    </w>
    <w>
     ein
    </w>
    <w>
     god
    </w>
    <w>
     Vén
    </w>
    <w>
     ,
    </w>
    <w>
     sa
    </w>
    <w>
     ho
    </w>
    <w>
     ,
    </w>
    <w>
     berre
    </w>
    <w>
     det
    </w>
    <w>
     var
    </w>
    <w>
     ein
    </w>
    <w>
     ho
    </w>
    <w>
     kunde
    </w>
    <w>
     lite
    </w>
    <w>
     paa
    </w>
    <w>
     ;
    </w>
    <w>
     for
    </w>
    <w>
     det
    </w>
    <w>
     var
    </w>
    <w>
     meir
    </w>
    <w>
     stuslegt
    </w>
    <w>
     enn
    </w>
    <w>
     nokon
    </w>
    <w>
     vilde
    </w>
    <w>
     tru
    </w>
    <w>
     aa
    </w>
    <w>
     vera
    </w>
    <w>
     so
    </w>
    <w>
     reint
    </w>
    <w>
     aaleine
    </w>
    <w>
     .
    </w>
   </s>
   <s>
    <w>
     Ho
    </w>
    <w>
     hadde
    </w>
    <w>
     tidt
    </w>
    <w>
     tenkt
    </w>
    <w>
     at
    </w>
    <w>
     ho
    </w>
    <w>
     ikkje
    </w>
    <w>
     heldt
    </w>
    <w>
     det
    </w>
    <w>
     lengi
    </w>
    <w>
     ut
    </w>
    <w>
     ;
    </w>
    <w>
     og
    </w>
    <w>
     naar
    </w>
    <w>
     ein
    </w>
    <w>
     ingin
    </w>
    <w>
     hadde
    </w>
    <w>
     aa
    </w>
    <w>
     halde
    </w>
    <w>
     seg
    </w>
    <w>
     til
    </w>
    <w>
     ,
    </w>
    <w>
     kunde
    </w>
    <w>
     det
    </w>
    <w>
     snart
    </w>
    <w>
     gaa
    </w>
    <w>
     verre
    </w>
    <w>
     .
    </w>
   </s>
  </p>
 </sample>
 <sample>
  <p n="NOR0013620">
   <s>
    <w>
     Nei
    </w>
    <w>
     ,
    </w>
    <w>
     ikkje
    </w>
    <w>
     Emilie
    </w>
    <w>
     ,
    </w>
    <w>
     sa
    </w>
    <w>
     Georg
    </w>
    <w>
     rolegt
    </w>
    <w>
     .
    </w>
   </s>
  </p>
  <p n="NOR0013621"/>
  <p n="NOR0013622"/>
  <p n="NOR0013623">
   <s>
    <w>
     –
    </w>
    <w>
     Eller
    </w>
    <w>
     du
    </w>
    <w>
     kunde
    </w>
    <w>
     kalle
    </w>
    <w>
     meg
    </w>
    <w>
     Nina
    </w>
    <w>
     ?
    </w>
   </s>
  </p>
  <p n="NOR0013624"/>
  <p n="NOR0013625"/>
  <p n="NOR0013626"/>
  <p n="NOR0013627"/>
  <p n="NOR0013628"/>
  <p n="NOR0013629">
   <s>
    <w>
     –
    </w>
    <w>
     Aa
    </w>
    <w>
     nei
    </w>
    <w>
     vel
    </w>
    <w>
     ?
    </w>
   </s>
  </p>
  <p n="NOR0013630">
   <s>
    <w>
     –
    </w>
    <w>
     Aa
    </w>
    <w>
     naa
    </w>
    <w>
     .
    </w>
   </s>
  </p>
  <p n="NOR0013631">
   <s>
    <w>
     –
    </w>
    <w>
     Ja
    </w>
    <w>
     …
    </w>
    <w>
     du
    </w>
    <w>
     kunde
    </w>
    <w>
     kalle
    </w>
    <w>
     meg
    </w>
    <w>
     Eline
    </w>
    <w>
     og
    </w>
    <w>
     ;
    </w>
    <w>
     –
    </w>
    <w>
     det
    </w>
    <w>
     er
    </w>
    <w>
     den
    </w>
    <w>
     siste
    </w>
    <w>
     !
    </w>
   </s>
  </p>
  <p n="NOR0013632"/>
  <p n="NOR0013633">
   <s>
    <w>
     –
    </w>
    <w>
     Ja
    </w>
    <w>
     .
    </w>
   </s>
  </p>
  <p n="NOR0013634">
   <s>
    <w>
     –
    </w>
    <w>
     Ja
    </w>
    <w>
     .
    </w>
   </s>
   <s>
    <w>
     Ho
    </w>
    <w>
     er
    </w>
    <w>
     av
    </w>
    <w>
     Is
    </w>
    <w>
     .
    </w>
   </s>
  </p>
  <p n="NOR0013635">
   <s>
    <w>
     Han
    </w>
    <w>
     sette
    </w>
    <w>
     fram
    </w>
    <w>
     Flaske
    </w>
    <w>
     og
    </w>
    <w>
     Glas
    </w>
    <w>
     .
    </w>
   </s>
   <s>
    <w>
     Julie
    </w>
    <w>
     saag
    </w>
    <w>
     ut
    </w>
    <w>
     som
    </w>
    <w>
     ho
    </w>
    <w>
     vilde
    </w>
    <w>
     graate
    </w>
    <w>
     .
    </w>
   </s>
  </p>
  <p n="NOR0013636">
   <s>
    <w>
     Han
    </w>
    <w>
     sette
    </w>
    <w>
     seg
    </w>
    <w>
     upptil
    </w>
    <w>
     henne
    </w>
    <w>
     i
    </w>
    <w>
     Sofaen
    </w>
    <w>
     .
    </w>
   </s>
   <s>
    <w>
     No
    </w>
    <w>
     skal
    </w>
    <w>
     me
    </w>
    <w>
     vera
    </w>
    <w>
     intelligente
    </w>
    <w>
     ,
    </w>
    <w>
     Julie
    </w>
    <w>
     ,
    </w>
    <w>
     sa
    </w>
    <w>
     han
    </w>
    <w>
     .
    </w>
   </s>
   <s>
    <w>
     Lat
    </w>
    <w>
     Frøken
    </w>
    <w>
     Johnsen
    </w>
    <w>
     fara
    </w>
    <w>
     med
    </w>
    <w>
     Snakk
    </w>
    <w>
     ;
    </w>
    <w>
     ho
    </w>
    <w>
     hev
    </w>
    <w>
     ikkje
    </w>
    <w>
     anna
    </w>
    <w>
     aa
    </w>
    <w>
     gjera
    </w>
    <w>
     .
    </w>
   </s>
  </p>
  <p n="NOR0013637"/>
  <p n="NOR0013638">
   <s>
    <w>
     Du
    </w>
    <w>
     segjer
    </w>
    <w>
     eg
    </w>
    <w>
     skifter
    </w>
    <w>
     for
    </w>
    <w>
     tidt
    </w>
    <w>
     ,
    </w>
    <w>
     heldt
    </w>
    <w>
     han
    </w>
    <w>
     fram
    </w>
    <w>
     .
    </w>
   </s>
   <s>
    <w>
     Kva
    </w>
    <w>
     skal
    </w>
    <w>
     eg
    </w>
    <w>
     gjera
    </w>
    <w>
     ?
    </w>
   </s>
   <s>
    <w>
     Der
    </w>
    <w>
     er
    </w>
    <w>
     noko
    </w>
    <w>
     i
    </w>
    <w>
     Vegen
    </w>
    <w>
     med
    </w>
    <w>
     deim
    </w>
    <w>
     alle
    </w>
    <w>
     .
    </w>
   </s>
   <s>
    <w>
     Den
    </w>
    <w>
     eg
    </w>
    <w>
     no
    </w>
    <w>
     hev
    </w>
    <w>
     driv
    </w>
    <w>
     det
    </w>
    <w>
     med
    </w>
    <w>
     aa
    </w>
    <w>
     sova
    </w>
    <w>
     .
    </w>
   </s>
   <s>
    <w>
     Kor
    </w>
    <w>
     eg
    </w>
    <w>
     kjem
    </w>
    <w>
     ,
    </w>
    <w>
     og
    </w>
    <w>
     naar
    </w>
    <w>
     eg
    </w>
    <w>
     kjem
    </w>
    <w>
     ,
    </w>
    <w>
     so
    </w>
    <w>
     sit
    </w>
    <w>
     ho
    </w>
    <w>
     og
    </w>
    <w>
     søv
    </w>
    <w>
     .
    </w>
   </s>
   <s>
    <w>
     Eller
    </w>
    <w>
     ligg
    </w>
    <w>
     og
    </w>
    <w>
     søv
    </w>
    <w>
     ;
    </w>
    <w>
     eller
    </w>
    <w>
     stend
    </w>
    <w>
     og
    </w>
    <w>
     søv
    </w>
    <w>
     ;
    </w>
    <w>
     ho
    </w>
    <w>
     søv
    </w>
    <w>
     paa
    </w>
    <w>
     alle
    </w>
    <w>
     Maatar
    </w>
    <w>
     og
    </w>
    <w>
     i
    </w>
    <w>
     alle
    </w>
    <w>
     Høve
    </w>
    <w>
     ;
    </w>
    <w>
     ho
    </w>
    <w>
     kunde
    </w>
    <w>
     taka
    </w>
    <w>
     Eksamen
    </w>
    <w>
     i
    </w>
    <w>
     det
    </w>
    <w>
     ;
    </w>
    <w>
     ho
    </w>
    <w>
     er
    </w>
    <w>
     Spesialist
    </w>
    <w>
     .
    </w>
   </s>
   <s>
    <w>
     Fy
    </w>
    <w>
     for
    </w>
    <w>
     Satan
    </w>
    <w>
     ;
    </w>
    <w>
     det
    </w>
    <w>
     er
    </w>
    <w>
     so
    </w>
    <w>
     ein
    </w>
    <w>
     ærleg
    </w>
    <w>
     Mann
    </w>
    <w>
     kunde
    </w>
    <w>
     gifte
    </w>
    <w>
     seg
    </w>
    <w>
     !
    </w>
   </s>
   <s>
    <w>
     Det
    </w>
    <w>
     er
    </w>
    <w>
     nok
    </w>
    <w>
     sant
    </w>
    <w>
     at
    </w>
    <w>
     Mand
    </w>
    <w>
     og
    </w>
    <w>
     Kvinne
    </w>
    <w>
     treng
    </w>
    <w>
     kvarandre
    </w>
    <w>
     .
    </w>
   </s>
  </p>
  <p n="NOR0013639"/>
  <p n="NOR0013640">
   <s>
    <w>
     Han
    </w>
    <w>
     heldt
    </w>
    <w>
     fram
    </w>
    <w>
     .
    </w>
   </s>
   <s>
    <w>
     I
    </w>
    <w>
     huslege
    </w>
    <w>
     Spursmaal
    </w>
    <w>
     vilde
    </w>
    <w>
     han
    </w>
    <w>
     fylgje
    </w>
    <w>
     hennar
    </w>
    <w>
     Raadir
    </w>
    <w>
     so
    </w>
    <w>
     lengi
    </w>
    <w>
     han
    </w>
    <w>
     kunde
    </w>
    <w>
     .
    </w>
   </s>
   <s>
    <w>
     Dersom
    </w>
    <w>
     Laurits
    </w>
    <w>
     hadde
    </w>
    <w>
     sagt
    </w>
    <w>
     sant
    </w>
    <w>
     ,
    </w>
    <w>
     so
    </w>
    <w>
     var
    </w>
    <w>
     den
    </w>
    <w>
     nye
    </w>
    <w>
     Gjenta
    </w>
    <w>
     høveleg
    </w>
    <w>
     stygg
    </w>
    <w>
     og
    </w>
    <w>
     høveleg
    </w>
    <w>
     gamal
    </w>
    <w>
     ,
    </w>
    <w>
     stal
    </w>
    <w>
     eit
    </w>
    <w>
     Minimum
    </w>
    <w>
     ,
    </w>
    <w>
     og
    </w>
    <w>
     tagde
    </w>
    <w>
     som
    </w>
    <w>
     ein
    </w>
    <w>
     Fisk
    </w>
    <w>
     .
    </w>
   </s>
   <s>
    <w>
     Og
    </w>
    <w>
     so
    </w>
    <w>
     hadde
    </w>
    <w>
     ho
    </w>
    <w>
     eit
    </w>
    <w>
     svært
    </w>
    <w>
     gagnlegt
    </w>
    <w>
     Lyte
    </w>
    <w>
     .
    </w>
   </s>
   <s>
    <w>
     Ho
    </w>
    <w>
     var
    </w>
    <w>
     jaga
    </w>
    <w>
     fraa
    </w>
    <w>
     Plassen
    </w>
    <w>
     sin
    </w>
    <w>
     ,
    </w>
    <w>
     av
    </w>
    <w>
     di
    </w>
    <w>
     ho
    </w>
    <w>
     ikkje
    </w>
    <w>
     hadde
    </w>
    <w>
     vori
    </w>
    <w>
     streng
    </w>
    <w>
     nok
    </w>
    <w>
     mot
    </w>
    <w>
     Mannen
    </w>
    <w>
     i
    </w>
    <w>
     Huse
    </w>
    <w>
     ;
    </w>
    <w>
     –
    </w>
    <w>
     den
    </w>
    <w>
     store
    </w>
    <w>
     teologiske
    </w>
    <w>
     Slasken
    </w>
    <w>
     Braut
    </w>
    <w>
     ,
    </w>
    <w>
     han
    </w>
    <w>
     var
    </w>
    <w>
     etter
    </w>
    <w>
     henne
    </w>
    <w>
     ;
    </w>
    <w>
     han
    </w>
    <w>
     ;
    </w>
    <w>
     Heh
    </w>
    <w>
     .
    </w>
   </s>
   <s>
    <w>
     Dei
    </w>
    <w>
     Ægtemennane
    </w>
    <w>
     .
    </w>
   </s>
   <s>
    <w>
     Trur
    </w>
    <w>
     du
    </w>
    <w>
     dei
    </w>
    <w>
     er
    </w>
    <w>
     aa
    </w>
    <w>
     lite
    </w>
    <w>
     paa
    </w>
    <w>
     ,
    </w>
    <w>
     um
    </w>
    <w>
     dei
    </w>
    <w>
     gjeng
    </w>
    <w>
     med
    </w>
    <w>
     kvitt
    </w>
    <w>
     Slips
    </w>
    <w>
     ?
    </w>
   </s>
   <s>
    <w>
     Dersom
    </w>
    <w>
     du
    </w>
    <w>
     gifter
    </w>
    <w>
     deg
    </w>
    <w>
     ,
    </w>
    <w>
     Julie
    </w>
    <w>
     ,
    </w>
    <w>
     so
    </w>
    <w>
     gift
    </w>
    <w>
     deg
    </w>
    <w>
     med
    </w>
    <w>
     ein
    </w>
    <w>
     Mann
    </w>
    <w>
     som
    </w>
    <w>
     hev
    </w>
    <w>
     misst
    </w>
    <w>
     Tennane
    </w>
    <w>
     .
    </w>
   </s>
   <s>
    <w>
     –
    </w>
    <w>
     Men
    </w>
    <w>
     som
    </w>
    <w>
     sagt
    </w>
    <w>
     :
    </w>
    <w>
     forstend
    </w>
    <w>
     Gjenta
    </w>
    <w>
     at
    </w>
    <w>
     eg
    </w>
    <w>
     hev
    </w>
    <w>
     Greide
    </w>
    <w>
     paa
    </w>
    <w>
     henne
    </w>
    <w>
     i
    </w>
    <w>
     Præteritum
    </w>
    <w>
     ,
    </w>
    <w>
     so
    </w>
    <w>
     vert
    </w>
    <w>
     ho
    </w>
    <w>
     so
    </w>
    <w>
     blind
    </w>
    <w>
     som
    </w>
    <w>
     ein
    </w>
    <w>
     Vegg
    </w>
    <w>
     ,
    </w>
    <w>
     naar
    </w>
    <w>
     det
    </w>
    <w>
     er
    </w>
    <w>
     noko
    </w>
    <w>
     ho
    </w>
    <w>
     ikkje
    </w>
    <w>
     skal
    </w>
    <w>
     sjaa
    </w>
    <w>
     .
    </w>
   </s>
  </p>
 </sample>
</samples>